chuk_mcp_time/__init__.py
chuk_mcp_time/config.py
chuk_mcp_time/consensus.py
chuk_mcp_time/models.py
chuk_mcp_time/ntp_client.py
chuk_mcp_time/server.py
chuk_mcp_time/server.py.backup
chuk_mcp_time/timezone_utils.py
chuk_mcp_time-1.1.dist-info/METADATA
chuk_mcp_time-1.1.dist-info/WHEEL
chuk_mcp_time-1.1.dist-info/entry_points.txt
chuk_mcp_time-1.1.dist-info/licenses/LICENSE
chuk_mcp_time-1.1.dist-info/RECORD
