Metadata-Version: 2.4
Name: chuk-mcp-time
Version: 1.1
Summary: High-accuracy time oracle MCP server using NTP consensus and multiple time sources
Project-URL: Homepage, https://github.com/chuk-ai/chuk-mcp-time
Project-URL: Repository, https://github.com/chuk-ai/chuk-mcp-time
Project-URL: Issues, https://github.com/chuk-ai/chuk-mcp-time/issues
Author-email: Christopher Hay <chrishayuk@somejunkmailbox.com>
License: MIT
License-File: LICENSE
Keywords: consensus,mcp,ntp,oracle,time
Classifier: Development Status :: 4 - Beta
Classifier: Intended Audience :: Developers
Classifier: License :: OSI Approved :: MIT License
Classifier: Programming Language :: Python :: 3
Classifier: Programming Language :: Python :: 3.11
Classifier: Programming Language :: Python :: 3.12
Classifier: Programming Language :: Python :: 3.13
Requires-Python: >=3.11
Requires-Dist: chuk-mcp-server>=0.16.0
Requires-Dist: httpx>=0.27.0
Requires-Dist: pydantic-settings>=2.0.0
Requires-Dist: pydantic>=2.0.0
Requires-Dist: tzdata>=2024.1
Provides-Extra: dev
Requires-Dist: bandit>=1.7.0; extra == 'dev'
Requires-Dist: mypy>=1.8.0; extra == 'dev'
Requires-Dist: pytest-asyncio>=0.23.0; extra == 'dev'
Requires-Dist: pytest-cov>=4.1.0; extra == 'dev'
Requires-Dist: pytest>=8.0.0; extra == 'dev'
Requires-Dist: ruff>=0.3.0; extra == 'dev'
